aemcmc/__init__.py
aemcmc/_version.py
aemcmc/basic.py
aemcmc/conjugates.py
aemcmc/dists.py
aemcmc/ffbs.py
aemcmc/gibbs.py
aemcmc/nuts.py
aemcmc/rewriting.py
aemcmc/transforms.py
aemcmc/utils.py
aemcmc_nightly-0.0.6.dist-info/LICENSE
aemcmc_nightly-0.0.6.dist-info/METADATA
aemcmc_nightly-0.0.6.dist-info/WHEEL
aemcmc_nightly-0.0.6.dist-info/top_level.txt
aemcmc_nightly-0.0.6.dist-info/RECORD
