Metadata-Version: 2.1
Name: aemcmc-nightly
Version: 0.0.6
Summary: Miscellaneous MCMC samplers written in Aesara
Home-page: http://github.com/aesara-devs/aemcmc
Maintainer: Brandon T. Willard
Maintainer-email: aesara-devs@gmail.com
Keywords: math,probability,numerical,symbolic,MCMC
Classifier: Development Status :: 4 - Beta
Classifier: Intended Audience :: Science/Research
Classifier: Intended Audience :: Developers
Classifier: License :: OSI Approved :: MIT License
Classifier: Operating System :: OS Independent
Classifier: Programming Language :: Python
Classifier: Programming Language :: Python :: 3
Classifier: Programming Language :: Python :: 3.7
Classifier: Programming Language :: Python :: 3.8
Classifier: Programming Language :: Python :: 3.9
Classifier: Programming Language :: Python :: 3.10
Classifier: Programming Language :: Python :: Implementation :: CPython
Classifier: Programming Language :: Python :: Implementation :: PyPy
Requires-Python: >=3.7
License-File: LICENSE
Requires-Dist: numpy (>=1.18.1)
Requires-Dist: scipy (>=1.4.0)
Requires-Dist: aesara (>=2.8.3)
Requires-Dist: aeppl (>=0.0.40)
Requires-Dist: aehmc (>=0.0.10)
Requires-Dist: polyagamma (>=1.3.2)
Requires-Dist: cons
Requires-Dist: logical-unification
Requires-Dist: etuples
Requires-Dist: miniKanren
